odoo/addons/pos_remove_pos_category/README.rst
odoo/addons/pos_remove_pos_category/__init__.py
odoo/addons/pos_remove_pos_category/__manifest__.py
odoo/addons/pos_remove_pos_category/i18n/es.po
odoo/addons/pos_remove_pos_category/i18n/fr.po
odoo/addons/pos_remove_pos_category/i18n/it.po
odoo/addons/pos_remove_pos_category/i18n/nl_NL.po
odoo/addons/pos_remove_pos_category/i18n/pos_remove_pos_category.pot
odoo/addons/pos_remove_pos_category/models/__init__.py
odoo/addons/pos_remove_pos_category/models/module.py
odoo/addons/pos_remove_pos_category/models/product.py
odoo/addons/pos_remove_pos_category/static/description/icon.png
odoo/addons/pos_remove_pos_category/static/src/js/pos_remove_pos_category.js
odoo/addons/pos_remove_pos_category/views/assets.xml
odoo/addons/pos_remove_pos_category/views/pos_category_view.xml
odoo/addons/pos_remove_pos_category/views/pos_view.xml
odoo12_addon_pos_remove_pos_category-12.0.2.0.2.dist-info/METADATA
odoo12_addon_pos_remove_pos_category-12.0.2.0.2.dist-info/WHEEL
odoo12_addon_pos_remove_pos_category-12.0.2.0.2.dist-info/top_level.txt
odoo12_addon_pos_remove_pos_category-12.0.2.0.2.dist-info/RECORD
